llq/__init__.py
llq/base_operation_builder.py
llq/base_response.py
llq/schema.json
llq/schema.py
llq/clients/__init__.py
llq/clients/base_client.py
llq/clients/exception.py
llq/clients/graphql.py
llq/clients/rest.py
llq/fragments/__init__.py
llq/fragments/event.py
llq/fragments/fragment_builder.py
llq/fragments/job.py
llq/fragments/media_item.py
llq/fragments/organizer.py
llq/fragments/partner.py
llq/fragments/venue.py
llq/mutations/__init__.py
llq/mutations/auth.py
llq/mutations/job.py
llq/queries/__init__.py
llq/queries/event.py
llq/queries/job.py
llq/queries/partner.py
llq/rest_operations/__init__.py
llq/rest_operations/job.py
llq/type/__init__.py
llq/type/common.py
llq/type/node.py
llq/type/event/__init__.py
llq/type/job/__init__.py
llq/type/partner/__init__.py
llq_sdk-0.0.6.dist-info/METADATA
llq_sdk-0.0.6.dist-info/WHEEL
llq_sdk-0.0.6.dist-info/licenses/LICENSE
llq_sdk-0.0.6.dist-info/RECORD
