Metadata-Version: 2.4
Name: llq-sdk
Version: 0.0.6
Summary: Add your description here
Project-URL: Homepage, https://github.com/Le-Lab-Quantique/llq-sdk
Project-URL: Repository, https://github.com/Le-Lab-Quantique/llq-sdk
Project-URL: Changelog, https://github.com/Le-Lab-Quantique/llq-sdk/blob/main/CHANGELOG.md
Author-email: Angel Dijoux <angel.dijoux@yahoo.com>
License:                     GNU GENERAL PUBLIC LICENSE
License-File: LICENSE
Requires-Python: >=3.11
Requires-Dist: gql[aiohttp]>=3.5.0
Requires-Dist: inflection>=0.5.1
Requires-Dist: sgqlc>=16.4
Requires-Dist: uuid-utils>=0.10.0
Provides-Extra: dev
Requires-Dist: black<24.0,>=23.0; extra == 'dev'
Requires-Dist: build; extra == 'dev'
Requires-Dist: furo==2023.7.26; extra == 'dev'
Requires-Dist: isort<5.13,>=5.12; extra == 'dev'
Requires-Dist: mypy<1.5,>=1.0; extra == 'dev'
Requires-Dist: myst-parser<2.1,>=1.0; extra == 'dev'
Requires-Dist: pytest-asyncio>=0.24.0; extra == 'dev'
Requires-Dist: pytest-cov; extra == 'dev'
Requires-Dist: pytest>=8.3.2; extra == 'dev'
Requires-Dist: ruff; extra == 'dev'
Requires-Dist: setuptools; extra == 'dev'
Requires-Dist: wheel; extra == 'dev'
